{
    "authors": [
        "Hinda Koza-Culp"
    ],
    "date_download": "2017-02-15 15:16:04+00:00",
    "date_modify": null,
    "date_publish": "2017-02-15 10:11:18",
    "description": "New Trailer Features Songs, Gags and A Few Surprises",
    "filename": "http%3A%2F%2F1075koolfm.com%2Fwatch-extended-carpool-karaoke-trailer-released%2F.json",
    "image_url": "http://1075koolfm.com/wp-content/uploads/2017/02/Screenshot-228-e1487171391363-1000x499.png",
    "language": "en",
    "localpath": null,
    "maintext": "James Corden’s popular “Carpool Karaoke” segment from The Late Late Show is coming to Apple TV as a series in the near future. An extended trailer for the segment was released, and it looks like we are going to see some pretty hilarious celeb pairings- 16 of them to be exact.\nAlicia Keys, John Legend, Metallica, John Cena, Shaquille O’Neal, Will Smith and Ariana Grande are just some of the big names who will make an appearance.\nWill you be watching?\nCheck out the trailer below:",
    "source_domain": "1075koolfm.com",
    "title": "Watch: Extended ‘Carpool Karaoke’ Trailer Released",
    "title_page": null,
    "title_rss": null,
    "url": "http://1075koolfm.com/watch-extended-carpool-karaoke-trailer-released/"
}