{
    "authors": [
        "Abc News"
    ],
    "date_download": "2018-07-04 11:15:36+00:00",
    "date_modify": null,
    "date_publish": "2018-07-04 00:00:00",
    "description": "The massive 36-hour sales event offers members access to exclusive deals.",
    "filename": "https%3A%2F%2Fabcnews.go.com%2FTechnology%2Fvideo%2Famazon-prime-day-starts-july-16-56360003.json",
    "image_url": "https://s.abcnews.com/images/Technology/180704_atm_techbytes_hpMain_16x9_992.jpg",
    "language": "en",
    "localpath": null,
    "maintext": "Interest Successfully Added\nWe'll notify you here with news about AlertTag\nTurn on desktop notifications for breaking stories about interest?",
    "source_domain": "abcnews.go.com",
    "title": "Amazon Prime Day starts on July 16",
    "title_page": null,
    "title_rss": null,
    "url": "https://abcnews.go.com/Technology/video/amazon-prime-day-starts-july-16-56360003"
}