{
    "authors": [
        "Abc News"
    ],
    "date_download": "2017-02-15 14:51:36+00:00",
    "date_modify": null,
    "date_publish": "2017-02-15 00:00:00",
    "description": "Ambulance crash kills passenger en route to nursing home",
    "filename": "http%3A%2F%2Fabcnews.go.com%2FUS%2FwireStory%2Fambulance-crash-western-ny-kills-77-year-passenger-45506946.json",
    "image_url": "http://abcnews.go.com/US/wireStory/ambulance-crash-western-ny-kills-77-year-passenger-45506946",
    "language": "en",
    "localpath": null,
    "maintext": "Authorities say a 77-year-old western New York man has died after the ambulance transporting him from a Pennsylvania hospital to a nursing home crashed into a ditch.\nNew York State Police say an EmergyCare ambulance left the road at about 5:40 p.m. Tuesday, entered a ditch and hit a culvert in the Chautauqua (shuh-TAW'-kwuh) County town of Dunkirk, 35 miles southwest of Buffalo.\nTroopers say the ambulance was taking Arthur McArthur, of Dunkirk, from the University of Pittsburgh Medical Center in Erie to a nursing home in Chautauqua County. Police say McArthur suffered fatal injuries in the crash and was pronounced dead at the scene.\nThe ambulance's 49-year-old driver was treated at a local hospital for non-life-threatening injuries.\nThe crash is under investigation.",
    "source_domain": "abcnews.go.com",
    "title": "Ambulance crash kills passenger en route to nursing home",
    "title_page": null,
    "title_rss": null,
    "url": "http://abcnews.go.com/US/wireStory/ambulance-crash-western-ny-kills-77-year-passenger-45506946"
}