{
    "authors": [],
    "date_download": "2018-02-03 12:04:09+00:00",
    "date_modify": null,
    "date_publish": "2018-02-03 00:00:00",
    "description": null,
    "filename": "http%3A%2F%2Fbowienewsonline.com%2F2018%2F02%2Fcommunity-groups-ready-candidate-forums-in-time-for-march-primaries%2F.json",
    "image_url": "http://bowienewsonline.com/wp-content/uploads/2015/11/party-primary-graphic.jpg",
    "language": "en",
    "localpath": null,
    "maintext": "Two area organizations are planning candidate forums in February in preparation of the March 6 Texas party primaries.\n“Get out and vote” will be at 6 p.m. on Feb. 5 at The Carpenter Shop in Nocona. Join them for a soup supper and baked goods auction.\nThis is a fundraiser for Meals on Wheels, which will receive all the proceeds. Cost will be $5 for adults and $2.50 for children age 10 and under.\nOrganizers invite guests to bring questions for the candidates, but advise they will be monitored so the evening can be enlightening and enjoyable for voters and candidates states their flier.\nThe Amity Club will have its biennial Candidates Forum and Soup Supper on Feb. 15 at the Bowie Community Center, west end. Serving will begin at 5:30 p.m.\nPrice of admission is a donation to the club’s scholarship fund. There also will be a baked goods auction. Make plans to attend the events.",
    "source_domain": "bowienewsonline.com",
    "title": "Community groups ready candidate forums in time for March primaries",
    "title_page": null,
    "title_rss": null,
    "url": "http://bowienewsonline.com/2018/02/community-groups-ready-candidate-forums-in-time-for-march-primaries/"
}