{
    "authors": [],
    "date_download": "2017-04-17 16:27:25+00:00",
    "date_modify": null,
    "date_publish": "2017-04-12 19:33:55",
    "description": "Luis Fonsi and Daddy Yankee add Bieber to the mix.",
    "filename": "http%3A%2F%2Fb96.cbslocal.com%2F2017%2F04%2F17%2Fjustin-bieber-despacito-remix%2F.json",
    "image_url": "https://cbsb96radio.files.wordpress.com/2017/04/justin-bieber-jens-astrupafpgetty-image.jpg?w=946",
    "language": "en",
    "localpath": null,
    "maintext": "By Abby Hassler\nEver wanted to hear Justin Bieber singing in Spanish? Fans get their wish in Luis Fonsi and Daddy Yankee’s “Despacito” remix, where the singer starts the new track with a verse in English but switches over to Spanish for the chorus.\nRelated: Ringo Starr Confirms The Beatles are Bigger than Justin Bieber\nThe “Sorry” singer built up anticipation ahead of the track’s release by posting photos from his recording session on social media last week. One of the photos ended up being the cover for the remix.\nListen to the remix below.",
    "source_domain": "b96.cbslocal.com",
    "title": "Justin Bieber Sings in Spanish on ‘Despacito’ Remix",
    "title_page": null,
    "title_rss": null,
    "url": "http://b96.cbslocal.com/2017/04/17/justin-bieber-despacito-remix/"
}