{
    "authors": [],
    "date_download": "2017-02-14 23:46:13+00:00",
    "date_modify": null,
    "date_publish": "2017-02-14 22:37:38",
    "description": "A courthouse in Morgan Hill was evacuated Tuesday morning due to a suspicious package sent by a party in an ongoing case.",
    "filename": "http%3A%2F%2Fabc7news.com%2Fnews%2Fsuspicious-package-prompts-evacuation-of-morgan-hill-courthouse%2F1754832%2F.json",
    "image_url": "http://cdn.abclocal.go.com/assets/news/kgo/images/logos/default_800x450.jpg",
    "language": "en",
    "localpath": null,
    "maintext": "A courthouse in Morgan Hill was evacuated Tuesday morning due to a suspicious package sent by a party in an ongoing case.The courthouse was evacuated around 11:30 a.m., but it was unclear who brought the package into the building.The evacuation prompted officials to cancel proceedings for the rest of the day.The package was taken out of the building by Sheriff's deputies, and the bomb squad was called in.The street leading to the court was blocked off, and no further details were immediately available.",
    "source_domain": "abc7news.com",
    "title": "Suspicious package prompts evacuation of Morgan Hill courthouse",
    "title_page": null,
    "title_rss": null,
    "url": "http://abc7news.com/news/suspicious-package-prompts-evacuation-of-morgan-hill-courthouse/1754832/"
}