{
    "authors": [],
    "date_download": "2018-02-03 00:03:30+00:00",
    "date_modify": null,
    "date_publish": "2018-02-02 15:56:00",
    "description": "Police say the victim, a Surrey man who is known to them, is not co-operating with investigators.",
    "filename": "https%3A%2F%2Fbc.ctvnews.ca%2F20-year-old-man-injured-in-targeted-richmond-shooting-1.3787809.json",
    "image_url": "https://www.ctvnews.ca/polopoly_fs/1.3787812.1517615694!/httpImage/image.jpg_gen/derivatives/landscape_620/image.jpg",
    "language": "en",
    "localpath": null,
    "maintext": "CTV Vancouver\nA Surrey man is being treated in hospital following what police believe was a targeted shooting in Richmond.\nMounties were called to the 7000-block of Westminster Highway shortly before 10:30 p.m. Thursday for reports of the shooting. The 20-year-old victim was found suffering from injuries consistent with being shot.\nIt appeared that he had been shot near the 6200-block of Lynas Lane. Police were still on scene Friday, scouring the area for evidence with the help of a canine unit.\nThe victim, who is known to police, was taken to hospital for treatment and has been \"less than co-operative\" with investigators, the RCMP said.\nFew details have been provided about the incident, but Mounties said they believe it was targeted.\nPolice are canvassing the area for witnesses and surveillance camera footage.\nAnyone with information or video is asked to contact Cpl. Shawn Hazell at 604-278-1212, or to call Crime Stoppers anonymously at 1-800-222-8477 (TIPS).",
    "source_domain": "bc.ctvnews.ca",
    "title": "20-year-old man injured in targeted Richmond shooting",
    "title_page": null,
    "title_rss": null,
    "url": "https://bc.ctvnews.ca/20-year-old-man-injured-in-targeted-richmond-shooting-1.3787809"
}