{
    "authors": [],
    "date_download": "2017-10-06 20:45:58+00:00",
    "date_modify": null,
    "date_publish": "2017-10-06 00:00:00",
    "description": "Acts featured on the stream include Red Hot Chili Peppers, Gorillaz, Portugal. the Man and Tove Lo.",
    "filename": "http%3A%2F%2F931jackfm.cbslocal.com%2F2017%2F10%2F06%2Faustin-city-limits-festival-live-stream-2017%2F.json",
    "image_url": "https://cbs931jackfm.files.wordpress.com/2017/10/anthony-keidis-nyc.jpg?w=946",
    "language": "en",
    "localpath": null,
    "maintext": "By Scott T. Sterling\nMusic fans without tickets for this year’s massive Austin City Limits festival fret not. The fest will be live streaming sets from a wide variety of bands all weekend long.\nRelated: Flea Shuts Down Red Hot Chili Peppers Retirement Rumors\nAmong the acts set to be featured on the live stream include Red Hot Chili Peppers, Gorillaz, Portugal. the Man, Danny Brown, Tove Lo, the Brothers Osborne, Ryan Adams and more.\nSadly, two of the biggest names on the bill—JAY-Z and the Killers—will not be a part of the live stream.\nSee the complete lineup and watch ACL 2017 below.\nFriday, October 6\nChannel 1\n2:05pm — Asleep at the Wheel\n3:10pm — Mutemath\n4:15pm — Crystal Castles\n5:15pm — Lukas Nelson & Promise of the Real\n6:15pm — Royal Blood\n7:20pm — Ryan Adams\n8:30pm — Foster the People\nChannel 2\n2:05pm — MISSIO\n3:05pm — Sandy (Alex G)\n5:05pm — Andrew McMahon in the Wilderness\n6:05pm — Hamilton Leithauser\n7:05pm — Vulfpeck\n8:05pm — The Revivalists\nSaturday, October 7\nChannel 1\n2:05pm— MUNA\n2:55pm — A$AP Ferg\n4:00pm — Joseph\n5:00pm — LIVE\n6:05pm — Cut Copy\n7:10pm — Spoon\n8:15pm — Red Hot Chili Peppers\nChannel 2\n2:05pm — Welles\n3:00pm — DREAMCAR\n4:00pm — Benjamin Booker\n5:05pm — Cody Jinks\n6:05pm — Angel Olsen\n7:05pm — Tove Lo\n8:05pm — The Black Angels\nSunday, October 8\nChannel 1\n2:05pm — Middle Kids\n3:15pm — Brothers Osborne\n4:20pm — Milky Chance\n5:25pm — The Growlers\n6:30pm — Run the Jewels\n7:35pm — Portugal.the Man\nChannel 2\n2:05pm — Amy Shark\n2:50pm — Sam Dew\n3:50pm — Danny Brown\n4:50pm — D.R.A.M.\n5:50pm — Louis the Child\n6:50pm — First Aid Kit\n7:50pm — The Head and the Heart\n8:50pm — Gorillaz",
    "source_domain": "931jackfm.cbslocal.com",
    "title": "Watch the Austin City Limits Festival Live Stream",
    "title_page": null,
    "title_rss": null,
    "url": "http://931jackfm.cbslocal.com/2017/10/06/austin-city-limits-festival-live-stream-2017/"
}